README.md
megalib.py
setup.cfg
setup.py
megaLib.egg-info/PKG-INFO
megaLib.egg-info/SOURCES.txt
megaLib.egg-info/dependency_links.txt
megaLib.egg-info/requires.txt
megaLib.egg-info/top_level.txt