Metadata-Version: 2.1
Name: megaLib
Version: 0.9.4.1
Summary: megaLib is a Python wrapper for the Megaport RESTful API
Home-page: https://github.com/jvdspeare/megaLib
Author: james.speare
Author-email: info.megalib@gmail.com
License: GPLv3
Platform: UNKNOWN
